Workbook

Sheet Assumptions
A1: Key | B1: Value | C1: Notes
A2: Country | B2: Canada | C2: Target market / country
A3: Currency | B3: CAD | C3: Currency for all values in this sheet
A4: TAM (total drivers) | B4: 400000 | C4: Estimated total addressable market (Canada - gig/active drivers)
A5: Default SOM % | B5: 0.05 | C5: Serviceable obtainable market %
A6: price_standard (CAD/yr) | B6: 79 | C6: Standard annual price (CAD)
A7: price_pro (CAD/yr) | B7: 149 | C7: Pro annual price (CAD)
A8: default_pro_pct | B8: 0.7 | C8: Default percent of paid users on Pro
A9: CAC (CAD) | B9: 70 | C9: Cost to acquire a paid user (CAD)
A10: Gross Margin | B10: 0.8 | C10: Gross margin on subscription revenue
A11: Lifetime (years) | B11: 2 | C11: Average paid user lifetime (years)
A12: growth_conservative | B12: 0.1 | C12: Annual growth rate for paying users (conservative)
A13: growth_base | B13: 0.3 | C13: Annual growth rate for paying users (base)
A14: growth_optimistic | B14: 0.6 | C14: Annual growth rate for paying users (optimistic)
A15: annual_cost_growth | B15: 0.03 | C15: Annual growth rate for operating costs
... A17: OPS_ANNUAL (CAD) | B17: 300000 | C17: Annual operating cost (CAD)

Sheet Scenarios
A1: Scenario | B1: SOM_pct | C1: Conv_rate | D1: ActiveUsers | E1: PayingUsers | F1: Pro_pct | G1: ARPU | H1: Revenue | I1: CAC | J1: AcquisitionCost | K1: GrossProfit | L1: NetProfit | M1: LTV | N1: LTV/CAC
A2: Conservative | B2: 0.02 | C2: 0.03 | D2: =Assumptions!$B$2 * B2 -> #VALUE! | E2: =D2 * C2 -> #VALUE! | F2: 0.7 | G2: =Assumptions!$B$3*(1-F2) + Assumptions!$B$4*F2 -> #VALUE! | H2: =E2 * G2 -> #VALUE! | I2: =Assumptions!$B$6 -> 79 | J2: =E2 * I2 -> #VALUE! | K2: =H2 * Assumptions!$B$7 -> #VALUE! | L2: =K2 - J2 - Assumptions!$B$10 - Assumptions!$B$9 -> #VALUE! | M2: =G2 * Assumptions!$B$7 * Assumptions!$B$8 -> #VALUE! | N2: =M2 / I2 -> #VALUE!
A3: Base | B3: 0.05 | C3: 0.05 | D3: =Assumptions!$B$2 * B3 -> #VALUE! | E3: =D3 * C3 -> #VALUE! | F3: 0.7 | G3: =Assumptions!$B$3*(1-F3) + Assumptions!$B$4*F3 -> #VALUE! | H3: =E3 * G3 -> #VALUE! | I3: =Assumptions!$B$6 -> 79 | J3: =E3 * I3 -> #VALUE! | K3: =H3 * Assumptions!$B$7 -> #VALUE! | L3: =K3 - J3 - Assumptions!$B$10 - Assumptions!$B$9 -> #VALUE! | M3: =G3 * Assumptions!$B$7 * Assumptions!$B$8 -> #VALUE! | N3: =M3 / I3 -> #VALUE!
A4: Optimistic | B4: 0.1 | C4: 0.08 | D4: =Assumptions!$B$2 * B4 -> #VALUE! | E4: =D4 * C4 -> #VALUE! | F4: 0.7 | G4: =Assumptions!$B$3*(1-F4) + Assumptions!$B$4*F4 -> #VALUE! | H4: =E4 * G4 -> #VALUE! | I4: =Assumptions!$B$6 -> 79 | J4: =E4 * I4 -> #VALUE! | K4: =H4 * Assumptions!$B$7 -> #VALUE! | L4: =K4 - J4 - Assumptions!$B$10 - Assumptions!$B$9 -> #VALUE! | M4: =G4 * Assumptions!$B$7 * Assumptions!$B$8 -> #VALUE! | N4: =M4 / I4 -> #VALUE!

Sheet UnitEconomics
A1: Metric | B1: Formula / Value
A2: ARPU example (mix 30% standard,70% pro) | B2: =0.3*Assumptions!$B$3 + 0.7*Assumptions!$B$4 -> #VALUE!
A3: LTV example | B3: =B2 * Assumptions!$B$7 * Assumptions!$B$8 -> #VALUE!
A4: CAC (assumption) | B4: =Assumptions!$B$6 -> 79
A5: LTV/CAC (example) | B5: =B3 / B4 -> #VALUE!
A6: CAC Payback (months) example | B6: =Assumptions!$B$6 / ((0.3*Assumptions!$B$3 + 0.7*Assumptions!$B$4)/12) -> #VALUE!

Sheet Costs
A1: Cost Category | B1: Line Item | C1: Annual (CAD) | D1: Notes
A2: Development | B2: Frontend devs (salaries/contract) | C2: 180000 | D2: Year 1 estimate, CAD
A3: Development | B3: Backend devs & API | C3: 150000 | D3: Year 1 estimate, CAD
A4: Development | B4: QA / Testing | C4: 30000 | D4: Year 1 estimate, CAD
A5: Development | B5: DevOps / Infra setup | C5: 20000 | D5: One-time infra setup, CAD
A6: Infrastructure | B6: Hosting (annual) | C6: 36000 | D6: Cloud hosting, scaling
A7: Infrastructure | B7: CDN / Maps / APIs | C7: 12000 | D7: Third-party API costs (maps, data)
A8: Marketing | B8: Paid Ads & UA | C8: 90000 | D8: Annual marketing budget, CAD
A9: Marketing | B9: Content & SEO | C9: 18000 | D9: Ongoing content, CAD
A10: Sales | B10: Promotions / Discounts | C10: 12000 | D10: Promotional credits, CAD
A11: Support | B11: Customer support (annual) | C11: 48000 | D11: Support staff, CAD
A12: Legal & Finance | B12: Legal / Compliance | C12: 15000 | D12: Legal fees, CAD
A13: Legal & Finance | B13: Payment processing fees | C13: 12000 | D13: Estimated fees on revenue
... A15: One-time | B15: MVP design & research | C15: 25000 | D15: One-time UX / research costs
B16: Total Annual Costs | C16: =SUM(C2:C15) -> 658000 | D16: Sum of annual cost lines (excl one-time)

Sheet Scenarios_Numeric
A1: Scenario | B1: ActiveUsers | C1: PayingUsers | D1: ARPU | E1: Revenue | F1: AcquisitionCost | G1: GrossProfit | H1: NetProfit | I1: LTV | J1: LTV/CAC
A2: Conservative | B2: 8000 | C2: 240 | D2: 128 | E2: 30720 | F2: 16800 | G2: 24576 | H2: -1375224 | I2: 204.8 | J2: 2.93
A3: Base | B3: 20000 | C3: 1000 | D3: 128 | E3: 128000 | F3: 70000 | G3: 102400 | H3: -1350600 | I3: 204.8 | J3: 2.93
A4: Optimistic | B4: 40000 | C4: 3200 | D4: 128 | E4: 409600 | F4: 224000 | G4: 327680 | H4: -1279320 | I4: 204.8 | J4: 2.93

Sheet Projection_3yr
A1: Scenario | B1: Year | C1: PayingUsers | D1: Revenue | E1: TotalCosts | F1: NetProfit
A2: Conservative | B2: 1 | C2: 240 | D2: 30720 | E2: 1383000 | F2: -1375224
A3: Conservative | B3: 2 | C3: 264 | D3: 33792 | E3: 960990 | F3: -952436.4
A4: Conservative | B4: 3 | C4: 290 | D4: 37120 | E4: 989819.7 | F4: -980423.7
A5: Base | B5: 1 | C5: 1000 | D5: 128000 | E5: 1383000 | F5: -1350600
A6: Base | B6: 2 | C6: 1300 | D6: 166400 | E6: 960990 | F6: -918870
A7: Base | B7: 3 | C7: 1690 | D7: 216320 | E7: 989819.7 | F7: -935063.7
A8: Optimistic | B8: 1 | C8: 3200 | D8: 409600 | E8: 1383000 | F8: -1279320
A9: Optimistic | B9: 2 | C9: 5120 | D9: 655360 | E9: 960990 | F9: -795102
A10: Optimistic | B10: 3 | C10: 8192 | D10: 1048576 | E10: 989819.7 | F10: -724398.9
