Workbook

Sheet Assumptions
A1: Key | B1: Value | C1: Notes
A2: TAM (total drivers) | B2: 5000000 | C2: Total addressable market (US)
A3: Default SOM % | B3: 0.05 | C3: Serviceable obtainable market %
A4: price_standard (USD/yr) | B4: 59 | C4: Standard annual price
A5: price_pro (USD/yr) | B5: 119 | C5: Pro annual price
A6: default_pro_pct | B6: 0.7 | C6: Default percent of paid users on Pro
A7: CAC (USD) | B7: 50 | C7: Cost to acquire a paid user
A8: Gross Margin | B8: 0.8 | C8: Gross margin on subscription revenue
A9: Lifetime (years) | B9: 2 | C9: Average paid user lifetime (years)
A10: DEV_ONE_OFF (USD) | B10: 333000 | C10: One-time development cost (Year 1)
A11: OPS_ANNUAL (USD) | B11: 250000 | C11: Annual operating cost

Sheet Scenarios
A1: Scenario | B1: SOM_pct | C1: Conv_rate | D1: ActiveUsers | E1: PayingUsers | F1: Pro_pct | G1: ARPU | H1: Revenue | I1: CAC | J1: AcquisitionCost | K1: GrossProfit | L1: NetProfit | M1: LTV | N1: LTV/CAC
A2: Conservative | B2: 0.02 | C2: 0.03 | D2: =Assumptions!$B$2 * B2 | E2: =D2 * C2 | F2: 0.7 | G2: =Assumptions!$B$3*(1-F2) + Assumptions!$B$4*F2 | H2: =E2 * G2 | I2: =Assumptions!$B$6 | J2: =E2 * I2 | K2: =H2 * Assumptions!$B$7 | L2: =K2 - J2 - Assumptions!$B$10 - Assumptions!$B$9 | M2: =G2 * Assumptions!$B$7 * Assumptions!$B$8 | N2: =M2 / I2
A3: Base | B3: 0.05 | C3: 0.05 | D3: =Assumptions!$B$2 * B3 | E3: =D3 * C3 | F3: 0.7 | G3: =Assumptions!$B$3*(1-F3) + Assumptions!$B$4*F3 | H3: =E3 * G3 | I3: =Assumptions!$B$6 | J3: =E3 * I3 | K3: =H3 * Assumptions!$B$7 | L3: =K3 - J3 - Assumptions!$B$10 - Assumptions!$B$9 | M3: =G3 * Assumptions!$B$7 * Assumptions!$B$8 | N3: =M3 / I3
A4: Optimistic | B4: 0.1 | C4: 0.08 | D4: =Assumptions!$B$2 * B4 | E4: =D4 * C4 | F4: 0.7 | G4: =Assumptions!$B$3*(1-F4) + Assumptions!$B$4*F4 | H4: =E4 * G4 | I4: =Assumptions!$B$6 | J4: =E4 * I4 | K4: =H4 * Assumptions!$B$7 | L4: =K4 - J4 - Assumptions!$B$10 - Assumptions!$B$9 | M4: =G4 * Assumptions!$B$7 * Assumptions!$B$8 | N4: =M4 / I4

Sheet UnitEconomics
A1: Metric | B1: Formula / Value
A2: ARPU example (mix 30% standard,70% pro) | B2: =0.3*Assumptions!$B$3 + 0.7*Assumptions!$B$4
A3: LTV example | B3: =B2 * Assumptions!$B$7 * Assumptions!$B$8
A4: CAC (assumption) | B4: =Assumptions!$B$6
A5: LTV/CAC (example) | B5: =B3 / B4
A6: CAC Payback (months) example | B6: =Assumptions!$B$6 / ((0.3*Assumptions!$B$3 + 0.7*Assumptions!$B$4)/12)
